logseq/__init__.py
logseq/migration/__init__.py
logseq/migration/migrater.py
logseq/migration/monitor.py
logseq_migration-0.3.1.dist-info/LICENSE
logseq_migration-0.3.1.dist-info/METADATA
logseq_migration-0.3.1.dist-info/WHEEL
logseq_migration-0.3.1.dist-info/entry_points.txt
logseq_migration-0.3.1.dist-info/top_level.txt
logseq_migration-0.3.1.dist-info/RECORD
