Metadata-Version: 2.1
Name: logseq-migration
Version: 0.3.1
Summary: Download and use local copies of assets in logseq after importing a file from Roam.
Home-page: https://github.com/romilly/logseq-mirgation
Author: Romilly Cocking
Author-email: romilly.cocking@gmail.com
Project-URL: Bug Tracker, https://github.com/romilly/logseq-mirgation/issues
Classifier: Programming Language :: Python :: 3
Classifier: License :: OSI Approved :: MIT License
Classifier: Operating System :: OS Independent
Requires-Python: >=3.8
License-File: LICENSE
Requires-Dist: requests
Requires-Dist: PyHamcrest
